tgw/__init__.py
tgw/base_struct.py
tgw/cert_install.py
tgw/error_code.py
tgw/interface.py
tgw/server_spi.py
tgw/tmp_spi.py
tgw/cert/.ca.crt
tgw/common_linux_lib64/.ca.crt
tgw/common_linux_lib64/libaaf.so
tgw/common_linux_lib64/libadk.so
tgw/common_linux_lib64/libami.so
tgw/common_linux_lib64/libamigrpc++.so
tgw/common_linux_lib64/libamigrpc.so
tgw/common_linux_lib64/libcrypto.so.10
tgw/common_linux_lib64/libentry_wrapper.so
tgw/common_linux_lib64/libfmdutil.so
tgw/common_linux_lib64/libllmi.so
tgw/common_linux_lib64/libpcap.so.1
tgw/common_linux_lib64/librmm.so
tgw/common_linux_lib64/librum.so
tgw/common_linux_lib64/libsample_engine.so
tgw/common_linux_lib64/libssh.so.4
tgw/common_linux_lib64/libssl.so.10
tgw/common_linux_lib64/libtgw.so
tgw/common_linux_lib64/libz.so.1
tgw/linux_py36_x64_package/__init__.py
tgw/linux_py36_x64_package/libtgw_python36.so
tgw/linux_py36_x64_package/tgw.py
tgw/linux_py38_x64_package/__init__.py
tgw/linux_py38_x64_package/libtgw_python38.so
tgw/linux_py38_x64_package/tgw.py
tgw/win_py36_x64_package/.ca.crt
tgw/win_py36_x64_package/__init__.py
tgw/win_py36_x64_package/_tgw.pyd
tgw/win_py36_x64_package/boost_random-vc140-mt-1_62.dll
tgw/win_py36_x64_package/boost_system-vc140-mt-1_62.dll
tgw/win_py36_x64_package/libcrypto-1_1-x64.dll
tgw/win_py36_x64_package/libssl-1_1-x64.dll
tgw/win_py36_x64_package/tgw.dll
tgw/win_py36_x64_package/tgw.lib
tgw/win_py36_x64_package/tgw.py
tgw/win_py38_x64_package/.ca.crt
tgw/win_py38_x64_package/__init__.py
tgw/win_py38_x64_package/_tgw.pyd
tgw/win_py38_x64_package/boost_random-vc140-mt-1_62.dll
tgw/win_py38_x64_package/boost_system-vc140-mt-1_62.dll
tgw/win_py38_x64_package/libcrypto-1_1-x64.dll
tgw/win_py38_x64_package/libssl-1_1-x64.dll
tgw/win_py38_x64_package/tgw.dll
tgw/win_py38_x64_package/tgw.lib
tgw/win_py38_x64_package/tgw.py
tgw-1.0.5.1.dist-info/METADATA
tgw-1.0.5.1.dist-info/WHEEL
tgw-1.0.5.1.dist-info/top_level.txt
tgw-1.0.5.1.dist-info/RECORD
