Metadata-Version: 2.1
Name: tgw
Version: 1.0.5.1
Summary: 中国银河证券股份有限公司星耀数智服务平台python开发包
Home-page: http://www.chinastock.com.cn/newsite/cgs-services/strategyTrade/geWuInstitution.html
Author: China Galaxy Securities Co.,Ltd.
License: chinastock_tgw_sdk_python
Keywords: tgw 星耀 数据服务 银河 金融数据 chinastock
Platform: UNKNOWN
Requires-Dist: pandas
